ensemble_core/__init__.py
ensemble_core/login.py
ensemble_core-0.1.2.dist-info/METADATA
ensemble_core-0.1.2.dist-info/WHEEL
ensemble_core-0.1.2.dist-info/top_level.txt
ensemble_core-0.1.2.dist-info/RECORD
