Metadata-Version: 2.1
Name: ensemble-core
Version: 0.1.2
Summary: Ensemble-AI Company, generator & transformer
Home-page: https://github.com/SirAlex900/ensemble_core
Author: Chenwei Xu
Author-email: q1062327596@gmail.com
Requires-Dist: requests
Requires-Dist: torch
Requires-Dist: boto3
